Authwave/Authenticator.py
Authwave/AuthwaveException.py
Authwave/BaseProviderUri.py
Authwave/BaseResponseData.py
Authwave/IncompatableRedirectHandlerException.py
Authwave/InsecureProtocolException.py
Authwave/InvalidUserDataSerializationException.py
Authwave/LoginUri.py
Authwave/LogoutUri.py
Authwave/NotLoggedInException.py
Authwave/PortOutOfBoundsException.py
Authwave/RedirectHandler.py
Authwave/ResponseCipherDecryptionException.py
Authwave/SessionData.py
Authwave/SessionNotDictLikeException.py
Authwave/Token.py
Authwave/User.py
Authwave/UserResponseData.py
Authwave/__init__.py
Authwave/Cipher/AbstractMessage.py
Authwave/Cipher/CipherException.py
Authwave/Cipher/CipherText.py
Authwave/Cipher/DecryptionFailureException.py
Authwave/Cipher/EncryptedMessage.py
Authwave/Cipher/InitVector.py
Authwave/Cipher/Key.py
Authwave/Cipher/PlainTextMessage.py
Authwave/Cipher/__init__.py
Authwave/tests/Authenticator_test.py
Authwave/tests/SessionData_test.py
Authwave/tests/__init__.py
Authwave/tests/token_test.py
Authwave-0.0.1.dist-info/METADATA
Authwave-0.0.1.dist-info/WHEEL
Authwave-0.0.1.dist-info/top_level.txt
Authwave-0.0.1.dist-info/RECORD
