Metadata-Version: 2.1
Name: Authwave
Version: 0.0.1
Requires-Dist: pysodium (==0.7.12)
